odoo/addons/ssi_stock_canvas_operation/README.rst
odoo/addons/ssi_stock_canvas_operation/__init__.py
odoo/addons/ssi_stock_canvas_operation/__manifest__.py
odoo/addons/ssi_stock_canvas_operation/data/location_type_data.xml
odoo/addons/ssi_stock_canvas_operation/data/stock_picking_type_category_data.xml
odoo/addons/ssi_stock_canvas_operation/models/__init__.py
odoo/addons/ssi_stock_canvas_operation/models/res_partner.py
odoo/addons/ssi_stock_canvas_operation/security/ir_module_category_data.xml
odoo/addons/ssi_stock_canvas_operation/security/res_group_data.xml
odoo/addons/ssi_stock_canvas_operation/static/description/icon.png
odoo/addons/ssi_stock_canvas_operation/views/canvas_in_views.xml
odoo/addons/ssi_stock_canvas_operation/views/canvas_out_views.xml
odoo/addons/ssi_stock_canvas_operation/views/res_partner_views.xml
odoo/addons/ssi_stock_canvas_operation/views/sale_canvas_views.xml
odoo14_addon_ssi_stock_canvas_operation-14.0.1.1.0.dist-info/METADATA
odoo14_addon_ssi_stock_canvas_operation-14.0.1.1.0.dist-info/WHEEL
odoo14_addon_ssi_stock_canvas_operation-14.0.1.1.0.dist-info/top_level.txt
odoo14_addon_ssi_stock_canvas_operation-14.0.1.1.0.dist-info/RECORD
